askocli-0.5.data/scripts/askocli
libaskocli/__init__.py
libaskocli/actions/__init__.py
libaskocli/actions/integrate.py
askocli-0.5.dist-info/LICENSE
askocli-0.5.dist-info/METADATA
askocli-0.5.dist-info/WHEEL
askocli-0.5.dist-info/top_level.txt
askocli-0.5.dist-info/RECORD
