Metadata-Version: 2.1
Name: askocli
Version: 0.5
Summary: Command line interface for a distant AskOmics
Home-page: https://github.com/askomics/askocli
Author: Xavier Garnier
Author-email: xavier.garnier@irisa.fr
License: AGPL
Download-URL: https://github.com/askomics/askocli/archive/0.5.tar.gz
Platform: Posix; MacOS X; Windows
Classifier: Development Status :: 4 - Beta
Classifier: Intended Audience :: Developers
Classifier: License :: OSI Approved :: GNU Affero General Public License v3
Classifier: Operating System :: OS Independent
Classifier: Topic :: Scientific/Engineering :: Bio-Informatics
Classifier: Programming Language :: Python :: 3
Classifier: Programming Language :: Python :: 3
Classifier: Programming Language :: Python :: 3.0
Classifier: Programming Language :: Python :: 3.1
Classifier: Programming Language :: Python :: 3.2
Classifier: Programming Language :: Python :: 3.3
Classifier: Programming Language :: Python :: 3.4
Classifier: Programming Language :: Python :: 3.5
Classifier: Programming Language :: Python :: 3.6
Requires-Dist: requests (>=2.4.3)
